[ {
  "patchName" : "Change package name",
  "options" : [ {
    "key" : "packageName",
    "value" : null
  } ]
}, {
  "patchName" : "Custom branding",
  "options" : [ {
    "key" : "YouTubeappName",
    "value" : "YouTube"
  }, {
    "key" : "YouTubeiconPath",
    "value" : "./revancify"
  } ]
}, {
  "patchName" : "Theme",
  "options" : [ {
    "key" : "darkThemeBackgroundColor",
    "value" : "@android:color/black"
  }, {
    "key" : "lightThemeBackgroundColor",
    "value" : "@android:color/white"
  }, {
    "key" : "splashScreenBackgroundColor",
    "value" : "?android:attr/colorBackground"
  } ]
} ]
